etpproto/__init__.py
etpproto/client_info.py
etpproto/connection.py
etpproto/endpoint_capability_kind.py
etpproto/error.py
etpproto/messages.py
etpproto/protocols/__init__.py
etpproto/protocols/channel_data_frame.py
etpproto/protocols/channel_data_load.py
etpproto/protocols/channel_streaming.py
etpproto/protocols/channel_subscribe.py
etpproto/protocols/core.py
etpproto/protocols/data_array.py
etpproto/protocols/dataspace.py
etpproto/protocols/discovery.py
etpproto/protocols/discovery_query.py
etpproto/protocols/growing_object.py
etpproto/protocols/growing_object_notification.py
etpproto/protocols/growing_object_query.py
etpproto/protocols/store.py
etpproto/protocols/store_notification.py
etpproto/protocols/store_query.py
etpproto/protocols/supported_types.py
etpproto/protocols/transaction.py
etpproto/py.typed
etpproto/uri.py
etpproto/utils.py
etpproto-1.0.7.dist-info/LICENSE
etpproto-1.0.7.dist-info/METADATA
etpproto-1.0.7.dist-info/WHEEL
etpproto-1.0.7.dist-info/entry_points.txt
etpproto-1.0.7.dist-info/RECORD
