Metadata-Version: 2.3
Name: etpproto
Version: 1.0.7
Summary: ETP protocol implementation
License: Apache-2.0
Keywords: ETP
Author: Lionel Untereiner
Author-email: lionel.untereiner@geosiris.com
Maintainer: Valentin Gauthier
Maintainer-email: valentin.gauthier@geosiris.com
Requires-Python: >=3.9, <4.0
Classifier: License :: OSI Approved :: Apache Software License
Classifier: Programming Language :: Python :: 3
Classifier: Programming Language :: Python :: 3.9
Classifier: Programming Language :: Python :: 3.10
Classifier: Programming Language :: Python :: 3.11
Classifier: Programming Language :: Python :: 3.12
Classifier: Programming Language :: Python :: 3.13
Requires-Dist: etptypes (>=1.0.12,<2.0.0)
Requires-Dist: fastavro (>=1.6.1,<2.0.0)
